whv/__init__.py
whv/github.py
whv/travisci.py
whv-0.0.1.dist-info/METADATA
whv-0.0.1.dist-info/WHEEL
whv-0.0.1.dist-info/top_level.txt
whv-0.0.1.dist-info/RECORD
