Metadata-Version: 2.1
Name: whv
Version: 0.0.1
Summary: Verify webhooks for various providers
Home-page: https://github.com/tmhmitchell/whv
Author: Tom Mitchell
License: UNKNOWN
Platform: UNKNOWN
Classifier: Programming Language :: Python :: 3.8
Requires-Dist: cryptography
Requires-Dist: requests
